gym_doom/__init__.py
gym_doom/config.py
gym_doom/doom_env.py
gym_doom/scenarios/basic.cfg
gym_doom/scenarios/basic.wad
gym_doom/scenarios/deadly_corridor.cfg
gym_doom/scenarios/deadly_corridor.wad
gym_doom/scenarios/deathmatch.cfg
gym_doom/scenarios/deathmatch.wad
gym_doom/scenarios/defend_the_center.cfg
gym_doom/scenarios/defend_the_center.wad
gym_doom/scenarios/defend_the_line.cfg
gym_doom/scenarios/defend_the_line.wad
gym_doom/scenarios/health_gathering.cfg
gym_doom/scenarios/health_gathering.wad
gym_doom/scenarios/my_way_home.cfg
gym_doom/scenarios/my_way_home.wad
gym_doom/scenarios/predict_position.cfg
gym_doom/scenarios/predict_position.wad
gym_doom/scenarios/take_cover.cfg
gym_doom/scenarios/take_cover.wad
gym_doom/utils/__init__.py
gym_doom/utils/cfg_parser.py
gym_doom/utils/utils.py
gym_doom/wrappers/__init__.py
gym_doom/wrappers/doom_wrap.py
gym_doom-1.0.dist-info/LICENSE
gym_doom-1.0.dist-info/METADATA
gym_doom-1.0.dist-info/WHEEL
gym_doom-1.0.dist-info/top_level.txt
gym_doom-1.0.dist-info/RECORD
