Metadata-Version: 2.1
Name: gym-doom
Version: 1.0
Summary: Gym environment for VizDoom
Home-page: https://github.com/MarvineGothic/gym_doom
Author: Sergiy Isakov
Author-email: marvine.si@gmail.com
License: UNKNOWN
Platform: UNKNOWN
Classifier: Programming Language :: Python :: 3
Classifier: License :: OSI Approved :: MIT License
Classifier: Operating System :: OS Independent
